hf_hydrodata/__init__.py
hf_hydrodata/data_catalog.py
hf_hydrodata/data_model_access.py
hf_hydrodata/fast_pfb_reader.py
hf_hydrodata/grid.py
hf_hydrodata/gridded.py
hf_hydrodata/point.py
hf_hydrodata/projection.py
hf_hydrodata/publish_model.py
hf_hydrodata-1.3.50.dist-info/LICENSE
hf_hydrodata-1.3.50.dist-info/METADATA
hf_hydrodata-1.3.50.dist-info/WHEEL
hf_hydrodata-1.3.50.dist-info/RECORD
