Metadata-Version: 2.1
Name: hf_hydrodata
Version: 1.3.50
Summary: hydroframe tools and utilities
License: MIT
Author: William M. Hasling
Requires-Python: >=3.9,<4.0
Classifier: License :: OSI Approved :: MIT License
Classifier: Programming Language :: Python :: 3
Classifier: Programming Language :: Python :: 3.9
Classifier: Programming Language :: Python :: 3.10
Classifier: Programming Language :: Python :: 3.11
Requires-Dist: dask (>=2020.12.0)
Requires-Dist: importlib-resources (>=5.10.0)
Requires-Dist: netcdf4 (==1.7.3)
Requires-Dist: numpy (>=1.23.5)
Requires-Dist: pftools (>=1.3.9)
Requires-Dist: pyproj (>=3.5.0)
Requires-Dist: pyshp (>=2.3.1)
Requires-Dist: requests (>=2.28.2)
Requires-Dist: rioxarray (>=0.13.4)
Requires-Dist: scipy (>=1.10.0)
Requires-Dist: shapely (>=2.0.2)
Requires-Dist: typing_extensions (>=4.14.0)
Requires-Dist: xarray (>=0.21.0)
